tfc_utilities/__init__.py
tfc_utilities/tf_utils.py
python_utilities_tfc-1.9.0.dist-info/METADATA
python_utilities_tfc-1.9.0.dist-info/WHEEL
python_utilities_tfc-1.9.0.dist-info/top_level.txt
python_utilities_tfc-1.9.0.dist-info/RECORD
