Metadata-Version: 2.1
Name: python-utilities-tfc
Version: 1.9.0
Summary: Utility functions to work with Terraform Cloud and manage Terraform state.
Author: Umar Khan
Author-email: umar.khan@thecloudmania.com
Classifier: Programming Language :: Python :: 3
Classifier: License :: OSI Approved :: MIT License
Classifier: Operating System :: OS Independent
Requires-Python: >=3.11
Requires-Dist: requests
